gdmixworkflow/__init__.py
gdmixworkflow/distributed_workflow.py
gdmixworkflow/fixed_effect_workflow_generator.py
gdmixworkflow/main.py
gdmixworkflow/random_effect_workflow_generator.py
gdmixworkflow/single_node_workflow.py
gdmixworkflow/workflow_generator.py
gdmixworkflow/common/__init__.py
gdmixworkflow/common/constants.py
gdmixworkflow/common/utils.py
gdmixworkflow/distributed/__init__.py
gdmixworkflow/distributed/container_ops.py
gdmixworkflow/distributed/resource/__init__.py
gdmixworkflow/distributed/resource/sparkapplication_component.yaml
gdmixworkflow/distributed/resource/tfjob_component.yaml
gdmixworkflow/single_node/__init__.py
gdmixworkflow/single_node/local_ops.py
gdmix_workflow-0.3.0.dist-info/METADATA
gdmix_workflow-0.3.0.dist-info/WHEEL
gdmix_workflow-0.3.0.dist-info/top_level.txt
gdmix_workflow-0.3.0.dist-info/RECORD
