Metadata-Version: 2.1
Name: gdmix-workflow
Version: 0.3.0
Summary: UNKNOWN
Home-page: UNKNOWN
License: BSD-2-CLAUSE
Platform: UNKNOWN
Classifier: Programming Language :: Python :: 3.7
Classifier: Intended Audience :: Science/Research
Classifier: Intended Audience :: Developers
Classifier: License :: OSI Approved
Requires-Python: >=3.7
Requires-Dist: setuptools (>=41.0.0)
Requires-Dist: gdmix-trainer (==0.3.0)
Requires-Dist: google-auth (==1.21.1)
Requires-Dist: kfp (==0.2.5)
